{
  "parent": "bountifulfares:bountiful_fares",
  "criteria": {
    "make_first_food": {
      "conditions": {
        "item": {
          "tag": "bountifulfares:meals"
        }
      },
      "trigger": "minecraft:consume_item"
    }
  },
  "display": {
    "announce_to_chat": true,
    "background": "minecraft:textures/block/farmland_moist.png",
    "description": {
      "translate": "advancement.bountifulfares.make_first_food.description"
    },
    "frame": "task",
    "hidden": false,
    "icon": {
      "item": "bountifulfares:bountiful_stew"
    },
    "show_toast": true,
    "title": {
      "translate": "advancement.bountifulfares.make_first_food"
    }
  },
  "requirements": [
    [
      "make_first_food"
    ]
  ],
  "sends_telemetry_event": true
}