{
  "parent": "minecraft:recipes/root",
  "criteria": {
    "has_hoary_apple": {
      "conditions": {
        "items": [
          {
            "items": [
              "bountifulfares:hoary_apple"
            ]
          }
        ]
      },
      "trigger": "minecraft:inventory_changed"
    },
    "has_the_recipe": {
      "conditions": {
        "recipe": "minecraft:hoary_apple_block"
      },
      "trigger": "minecraft:recipe_unlocked"
    }
  },
  "requirements": [
    [
      "has_hoary_apple",
      "has_the_recipe"
    ]
  ],
  "rewards": {
    "recipes": [
      "minecraft:hoary_apple_block"
    ]
  },
  "sends_telemetry_event": false
}