{
  "variants": {
    "facing=east,half=lower": {
      "model": "bountifulcuisine:block/white_jack_o_straw_lower",
      "y": 90
    },
    "facing=east,half=upper": {
      "model": "bountifulcuisine:block/white_jack_o_straw_upper",
      "y": 90
    },
    "facing=north,half=lower": {
      "model": "bountifulcuisine:block/white_jack_o_straw_lower"
    },
    "facing=north,half=upper": {
      "model": "bountifulcuisine:block/white_jack_o_straw_upper"
    },
    "facing=south,half=lower": {
      "model": "bountifulcuisine:block/white_jack_o_straw_lower",
      "y": 180
    },
    "facing=south,half=upper": {
      "model": "bountifulcuisine:block/white_jack_o_straw_upper",
      "y": 180
    },
    "facing=west,half=lower": {
      "model": "bountifulcuisine:block/white_jack_o_straw_lower",
      "y": 270
    },
    "facing=west,half=upper": {
      "model": "bountifulcuisine:block/white_jack_o_straw_upper",
      "y": 270
    }
  }
}